{
"data": [
{
"id": 1,
"label": "Albania",
"self": "https://staging.eiti.org/api/v1.0/implementing_country/1",
"iso2": "AL",
"iso3": "ALB",
"status": null,
"status_date": null,
"local_website": null,
"annual_report_file": null,
"reports": {
"2012": [
{
"commodity": "Gross Domestic Product - extractive industries (Gross Value Added)",
"id": "1",
"value": "623696682464",
"value_bool": null,
"value_text": null,
"unit": "USD",
"source": "<URL, or reference to section in EITI Report>"
},
{
"commodity": "Gross Domestic Product - all sectors",
"id": "1",
"value": "12654028436019",
"value_bool": null,
"value_text": null,
"unit": "USD",
"source": "2.6.1. Contribution to Albanian Economy"
},
{
"commodity": "Government revenue - extractive industries",
"id": "1",
"value": "79146919431",
"value_bool": null,
"value_text": null,
"unit": "USD",
"source": "2.6.2. Government’s revenue from the upstream oil, gas and mining sector"
},
{
"commodity": "Government revenue - all sectors",
"id": "1",
"value": "3196208530806",
"value_bool": null,
"value_text": null,
"unit": "USD",
"source": "2.6.2. Government’s revenue from the upstream oil, gas and mining sector"
},
{
"commodity": "Exports - extractive industries",
"id": "1",
"value": "710900473934",
"value_bool": null,
"value_text": null,
"unit": "USD",
"source": "2.6.5 Export from the extractive sector"
},
{
"commodity": "Exports - all sectors",
"id": "1",
"value": "2090883746864",
"value_bool": null,
"value_text": null,
"unit": "USD",
"source": "2.6.5 Export from the extractive sector"
},
{
"commodity": "Oil, volume",
"id": "1",
"value": "1029300",
"value_bool": null,
"value_text": null,
"unit": "ton",
"source": "2.2.3 Oil and gas production"
},
{
"commodity": "Gas, volume",
"id": "1",
"value": "13.1",
"value_bool": null,
"value_text": null,
"unit": "million Sm3 o.e.",
"source": "2.2.3 Oil and gas production"
},
{
"commodity": "Oil, volume",
"id": "1",
"value": "1024000",
"value_bool": null,
"value_text": null,
"unit": "ton",
"source": "<URL, or reference to section in EITI Report>"
},
{
"commodity": "Total revenue received?",
"id": "1",
"value": "328909952607",
"value_bool": null,
"value_text": null,
"unit": "USD",
"source": "2.6.2. Government’s revenue from the upstream oil, gas and mining sector"
},
{
"commodity": "Population",
"id": "1",
"value": "2",
"value_bool": "0",
"value_text": "",
"unit": "people",
"source": null
}
],
"2013": [
{
"commodity": "Gross Domestic Product - extractive industries (Gross Value Added)",
"id": "1",
"value": "5",
"value_bool": null,
"value_text": null,
"unit": "% of GDP",
"source": "Page 13 of EITI Report 2013-2014"
},
{
"commodity": "Gross Domestic Product - all sectors",
"id": "1",
"value": "7",
"value_bool": null,
"value_text": null,
"unit": "% of GDP",
"source": "Page 13 of EITI Report 2013-2014"
},
{
"commodity": "Government revenue - extractive industries",
"id": "1",
"value": "164881741",
"value_bool": null,
"value_text": null,
"unit": "USD",
"source": "Page 14 of EITI Report 2013-2014"
},
{
"commodity": "Government revenue - all sectors",
"id": "1",
"value": "171277200",
"value_bool": null,
"value_text": null,
"unit": "USD",
"source": "Page 14 of Report EITI 2013-2014"
},
{
"commodity": "Exports - extractive industries",
"id": "1",
"value": "96705",
"value_bool": null,
"value_text": null,
"unit": "ALL million",
"source": "Page 16 of Report EITI 2013-2014"
},
{
"commodity": "Exports - all sectors",
"id": "1",
"value": "100828",
"value_bool": null,
"value_text": null,
"unit": "ALL million",
"source": "Page 16 and 77 of Report EITI 2013-2014"
},
{
"commodity": "Oil, volume",
"id": "1",
"value": "1203637",
"value_bool": null,
"value_text": null,
"unit": "Ton",
"source": "Page 38 of Report EITI 2013-2014"
},
{
"commodity": "Gas, volume",
"id": "1",
"value": "22.5",
"value_bool": null,
"value_text": null,
"unit": "million Nm3",
"source": "Page 38 of Report EITI 2013-2014"
},
{
"commodity": "Total revenue received?",
"id": "1",
"value": "33.418773142531",
"value_bool": null,
"value_text": null,
"unit": "",
"source": "Page 29, 30 and 111 of EITI Report 2013-2014"
}
]
},
"metadata": {
"2012": {
"contact": {
"name": "Andrii Zherebko",
"email": "Azherebko@eiti.org",
"organisation": "EITI"
},
"year_start": "1325376000",
"year_end": "1356912000",
"currency_rate": "0.1055",
"currency_code": "ALL",
"sectors_covered": [
"Gas",
"Mining",
"Oil"
],
"reporting_organisations": {
"companies": "75",
"governmental_agencies": "2"
},
"web_report_links": [
{
"url": "https://eiti.org/files/albania_eiti_report-2013-2014_final.pdf",
"title": "",
"attributes": []
}
],
"disaggregated": {
"project": "0",
"revenue_stream": "1",
"company": "1"
}
},
"2013": {
"contact": {
"name": "Eni Bajraktari",
"email": "eni.bajraktari@eiti.gov.al",
"organisation": "EITI Albania"
},
"year_start": "1356998400",
"year_end": "1388448000",
"currency_rate": "0.1057",
"currency_code": "ALL",
"sectors_covered": [
"Gas",
"Mining",
"Oil",
"Other Sectors"
],
"reporting_organisations": {
"companies": "103",
"governmental_agencies": "11"
},
"web_report_links": [
{
"url": "http://www.albeiti.org/wp-content/uploads/2016/01/EITI-Report-2013-2014.pdf",
"title": null,
"attributes": []
}
],
"disaggregated": {
"project": "0",
"revenue_stream": "1",
"company": "1"
}
}
},
"licenses": {
"2013": {
"Public registry of licences, oil": "www.google.com.ar",
"Public registry of licences, mining": "www.google.com.ar"
}
},
"contracts": {
"2013": {
"Does the report address the government's policy on contract disclosure?": "1",
"Are contracts disclosed?": "2",
"Publicly available registry of contracts": "www.google.com"
}
},
"revenues": {
"2012": {
"government": "64766958",
"company": "64767138"
},
"2013": {
"government": "312251154",
"company": "311789716"
}
}
},
{
"id": 2,
"label": "Republic Philippines",
"self": "https://staging.eiti.org/api/v1.0/implementing_country/2",
"iso2": "PH",
"iso3": "PHL",
"status": null,
"status_date": null,
"local_website": null,
"annual_report_file": null,
"reports": null,
"metadata": [],
"licenses": null,
"contracts": null,
"revenues": null
},
{
"id": 5,
"label": "Republic of the Congo",
"self": "https://staging.eiti.org/api/v1.0/implementing_country/5",
"iso2": "CD",
"iso3": "COD",
"status": null,
"status_date": "1230768000",
"local_website": "http://www.itie-congo.org/",
"annual_report_file": null,
"reports": null,
"metadata": [],
"licenses": null,
"contracts": null,
"revenues": null
},
{
"id": 6,
"label": "Peru",
"self": "https://staging.eiti.org/api/v1.0/implementing_country/6",
"iso2": "PE",
"iso3": "PER",
"status": null,
"status_date": null,
"local_website": null,
"annual_report_file": null,
"reports": null,
"metadata": [],
"licenses": null,
"contracts": null,
"revenues": null
},
{
"id": 7,
"label": "Mongolia",
"self": "https://staging.eiti.org/api/v1.0/implementing_country/7",
"iso2": "MN",
"iso3": "MNG",
"status": null,
"status_date": null,
"local_website": null,
"annual_report_file": null,
"reports": null,
"metadata": [],
"licenses": null,
"contracts": null,
"revenues": null
},
{
"id": 11,
"label": "Sierra Leone",
"self": "https://staging.eiti.org/api/v1.0/implementing_country/11",
"iso2": "SL",
"iso3": "SLE",
"status": null,
"status_date": null,
"local_website": null,
"annual_report_file": null,
"reports": null,
"metadata": [],
"licenses": null,
"contracts": null,
"revenues": null
},
{
"id": 12,
"label": "Guinea",
"self": "https://staging.eiti.org/api/v1.0/implementing_country/12",
"iso2": "GN",
"iso3": "GIN",
"status": null,
"status_date": "1167609600",
"local_website": "http://www.itie-guinee.org/",
"annual_report_file": null,
"reports": null,
"metadata": [],
"licenses": null,
"contracts": null,
"revenues": null
},
{
"id": 13,
"label": "Guatemala ",
"self": "https://staging.eiti.org/api/v1.0/implementing_country/13",
"iso2": "GT",
"iso3": "GTM",
"status": null,
"status_date": null,
"local_website": null,
"annual_report_file": null,
"reports": null,
"metadata": [],
"licenses": null,
"contracts": null,
"revenues": null
},
{
"id": 14,
"label": "Bulgaria",
"self": "https://staging.eiti.org/api/v1.0/implementing_country/14",
"iso2": "BG",
"iso3": "BGR",
"status": null,
"status_date": null,
"local_website": null,
"annual_report_file": null,
"reports": null,
"metadata": [],
"licenses": null,
"contracts": null,
"revenues": null
},
{
"id": 15,
"label": "Norway",
"self": "https://staging.eiti.org/api/v1.0/implementing_country/15",
"iso2": "NO",
"iso3": "NOR",
"status": null,
"status_date": null,
"local_website": null,
"annual_report_file": null,
"reports": null,
"metadata": [],
"licenses": null,
"contracts": null,
"revenues": null
},
{
"id": 16,
"label": "Mexico",
"self": "https://staging.eiti.org/api/v1.0/implementing_country/16",
"iso2": "MX",
"iso3": "MEX",
"status": {
"tid": "74",
"language": "en",
"name": "Compliant"
},
"status_date": "1420070400",
"local_website": "www.mexico.org",
"annual_report_file": "https://staging.eiti.org/sites/default/files/annualreports/rapportconciliationitiemauritanie2013.pdf",
"reports": null,
"metadata": [],
"licenses": null,
"contracts": null,
"revenues": null
},
{
"id": 17,
"label": "Brazil",
"self": "https://staging.eiti.org/api/v1.0/implementing_country/17",
"iso2": "BR",
"iso3": "BRA",
"status": {
"tid": "75",
"language": "en",
"name": "Candidate"
},
"status_date": null,
"local_website": null,
"annual_report_file": null,
"reports": null,
"metadata": [],
"licenses": null,
"contracts": null,
"revenues": null
},
{
"id": 18,
"label": "Costa Rica",
"self": "https://staging.eiti.org/api/v1.0/implementing_country/18",
"iso2": "CR",
"iso3": "CRI",
"status": null,
"status_date": null,
"local_website": null,
"annual_report_file": null,
"reports": null,
"metadata": [],
"licenses": null,
"contracts": null,
"revenues": null
},
{
"id": 19,
"label": "Liberia",
"self": "https://staging.eiti.org/api/v1.0/implementing_country/19",
"iso2": "LR",
"iso3": "LBR",
"status": null,
"status_date": null,
"local_website": null,
"annual_report_file": null,
"reports": null,
"metadata": [],
"licenses": null,
"contracts": null,
"revenues": null
},
{
"id": 20,
"label": "Niger",
"self": "https://staging.eiti.org/api/v1.0/implementing_country/20",
"iso2": "NE",
"iso3": "NER",
"status": {
"tid": "76",
"language": "en",
"name": "Suspended"
},
"status_date": "1199145600",
"local_website": null,
"annual_report_file": null,
"reports": null,
"metadata": [],
"licenses": null,
"contracts": null,
"revenues": null
},
{
"id": 22,
"label": "Mali",
"self": "https://staging.eiti.org/api/v1.0/implementing_country/22",
"iso2": "ML",
"iso3": "MLI",
"status": null,
"status_date": null,
"local_website": null,
"annual_report_file": null,
"reports": null,
"metadata": [],
"licenses": null,
"contracts": null,
"revenues": null
},
{
"id": 23,
"label": "Argentina",
"self": "https://staging.eiti.org/api/v1.0/implementing_country/23",
"iso2": "AR",
"iso3": "ARG",
"status": {
"tid": "74",
"language": "en",
"name": "Compliant"
},
"status_date": "1262304000",
"local_website": "www.argentina.org",
"annual_report_file": null,
"reports": null,
"metadata": [],
"licenses": null,
"contracts": null,
"revenues": null
},
{
"id": 24,
"label": "Maldives",
"self": "https://staging.eiti.org/api/v1.0/implementing_country/24",
"iso2": "MV",
"iso3": "MDV",
"status": {
"tid": "75",
"language": "en",
"name": "Candidate"
},
"status_date": "1104537600",
"local_website": "www.argentina.org",
"annual_report_file": null,
"reports": null,
"metadata": [],
"licenses": null,
"contracts": null,
"revenues": null
},
{
"id": 25,
"label": "São Tomé and Príncipe",
"self": "https://staging.eiti.org/api/v1.0/implementing_country/25",
"iso2": "ST",
"iso3": "STP",
"status": {
"tid": "74",
"language": "en",
"name": "Compliant"
},
"status_date": "1325376000",
"local_website": "http://www.min-financas.st/index.php/pt/eiti",
"annual_report_file": null,
"reports": null,
"metadata": [],
"licenses": null,
"contracts": null,
"revenues": null
}
],
"count": 19,
"self": {
"title": "Self",
"href": "https://staging.eiti.org/api/v1.0/implementing_country"
}
}